wtfis/__about__.py
wtfis/__init__.py
wtfis/config.py
wtfis/exceptions.py
wtfis/main.py
wtfis/utils.py
wtfis/version.py
wtfis/clients/__init__.py
wtfis/clients/abuseipdb.py
wtfis/clients/base.py
wtfis/clients/greynoise.py
wtfis/clients/ip2location.py
wtfis/clients/ip2whois.py
wtfis/clients/ipinfo.py
wtfis/clients/ipwhois.py
wtfis/clients/shodan.py
wtfis/clients/types.py
wtfis/clients/urlhaus.py
wtfis/clients/virustotal.py
wtfis/handlers/__init__.py
wtfis/handlers/base.py
wtfis/handlers/domain.py
wtfis/handlers/ip.py
wtfis/models/__init__.py
wtfis/models/abuseipdb.py
wtfis/models/base.py
wtfis/models/greynoise.py
wtfis/models/ip2location.py
wtfis/models/ip2whois.py
wtfis/models/ipinfo.py
wtfis/models/ipwhois.py
wtfis/models/shodan.py
wtfis/models/types.py
wtfis/models/urlhaus.py
wtfis/models/virustotal.py
wtfis/ui/__init__.py
wtfis/ui/base.py
wtfis/ui/progress.py
wtfis/ui/theme.py
wtfis/ui/view.py
wtfis-0.14.0.dist-info/METADATA
wtfis-0.14.0.dist-info/WHEEL
wtfis-0.14.0.dist-info/entry_points.txt
wtfis-0.14.0.dist-info/licenses/LICENSE
wtfis-0.14.0.dist-info/RECORD
