Metadata-Version: 2.4
Name: wtfis
Version: 0.14.0
Summary: Passive hostname, domain and IP lookup tool for non-robots
Project-URL: Homepage, https://github.com/pirxthepilot/wtfis
Author-email: pirxthepilot <pirxthepilot@users.noreply.github.com>
License-Expression: MIT
License-File: LICENSE
Keywords: abuseipdb,greynoise,ipinfo,osint,passive lookup,security,shodan,urlhaus,virustotal,whois
Classifier: Development Status :: 4 - Beta
Classifier: Environment :: Console
Classifier: License :: OSI Approved :: MIT License
Classifier: Programming Language :: Python :: 3
Classifier: Topic :: Security
Requires-Python: >=3.8
Requires-Dist: pydantic~=2.10.6; python_version == '3.8'
Requires-Dist: pydantic~=2.12.5; python_version >= '3.9'
Requires-Dist: python-dotenv<2,>=1.1.0; python_version >= '3.9'
Requires-Dist: python-dotenv~=1.0.1; python_version == '3.8'
Requires-Dist: requests<3,>=2.32.3
Requires-Dist: rich<15,>=14.0.0
